{
    "영화_정보": {
        "movieCd": "20201502",
        "movieNm": "유미의 세포들 더 무비",
        "movieNmEn": "YUMI'S CELLS THE MOVIE",
        "prdtYear": "2024",
        "openDt": "20240403",
        "typeNm": "장편",
        "prdtStatNm": "개봉",
        "nationAlt": "한국",
        "genreAlt": "애니메이션",
        "repNationNm": "한국",
        "repGenreNm": "애니메이션",
        "directors": [],
        "companys": [
            {
                "companyCd": "20141388",
                "companyNm": "(주)로커스"
            },
            {
                "companyCd": "20228943",
                "companyNm": "스튜디오엔(주)"
            }
        ]
    },
    "리뷰_목록": [
        {
            "리뷰어_닉네임": "신상훈남",
            "별점": "4.0",
            "좋아요_수": "83",
            "댓글_수": "0",
            "영화_제목": "유미의 세포들 더 무비",
            "리뷰_본문_내용": "내가 만약 꿈을 이루지 못 한 채 현실과 타협하는 부모가 되어있다면, 내 자식은 꼭 꿈을 이루게 만들어주고 싶다"
        },
        {
            "리뷰어_닉네임": "서진",
            "별점": "3.0",
            "좋아요_수": "53",
            "댓글_수": "0",
            "영화_제목": "유미의 세포들 더 무비",
            "리뷰_본문_내용": "사랑세포가 그의 특별한 핑크색 수트를 벗어던지기까지.\n그래, 사랑만이 행복의 이유는 아니지.\n유미의 온전한 행복을 위해 마냥 애써주는 세포들이 그저 사랑스럽다."
        },
        {
            "리뷰어_닉네임": "JY",
            "별점": "3.0",
            "좋아요_수": "39",
            "댓글_수": "0",
            "영화_제목": "유미의 세포들 더 무비",
            "리뷰_본문_내용": "높은 완성도의 그래픽과\n세포들의 반응이 매력있게 다가오는데 반해\n\n인간파트가 매력이 없고\n디자인 측면에서도 부자연스러워\n\n못내 아쉬움이 크게 느껴진다\n\n그리고 중심이벤트의 파고가 약해서\n후반부의 진행이 억지스럽다는 단점도 존재"
        },
        {
            "리뷰어_닉네임": "다솜땅",
            "별점": "4.0",
            "좋아요_수": "26",
            "댓글_수": "0",
            "영화_제목": "유미의 세포들 더 무비",
            "리뷰_본문_내용": "그냥 어느날, 이런 내용이 좋아져 버렸다.\n때론 속으로 삭이고, 화내야하는데... 마음은,..\n마음이 하라는 대로 하지 않을 때도 있고,\n멀리있는 사람을 애타게 그리워하지만,\n현실은... 접점도 없다.\n자꾸 보게되고..그리워하고...\n하지만, 변하는 건 없다.\n그렇게..\n시간은 간다..\n#24.7.10 (428)"
        },
        {
            "리뷰어_닉네임": "한창성",
            "별점": "2.0",
            "좋아요_수": "25",
            "댓글_수": "1",
            "영화_제목": "유미의 세포들 더 무비",
            "리뷰_본문_내용": "주인공들은 그냥 2D 애니메이션으로 살렸으면 어땠을까?\n\n개성 없는 3D 작화와 공감 되지 않는 연기.\n\n너무 인위적이고 오글거리는 바비의 목소리.\n\n세포들의 캐릭터와 연기는 좋다!"
        },
        {
            "리뷰어_닉네임": "rlaalsrud0710",
            "별점": "2.0",
            "좋아요_수": "24",
            "댓글_수": "0",
            "영화_제목": "유미의 세포들 더 무비",
            "리뷰_본문_내용": "유미공...어쩌다 시크릿쥬쥬가 되셨소..."
        },
        {
            "리뷰어_닉네임": "임희봉",
            "별점": "3.5",
            "좋아요_수": "21",
            "댓글_수": "0",
            "영화_제목": "유미의 세포들 더 무비",
            "리뷰_본문_내용": "어느새 유미를 같이 응원하게 만드는 세포들의 마법, 놀라운 3D 애니메이션 비주얼의 퀄리티!"
        },
        {
            "리뷰어_닉네임": "5jp",
            "별점": "3.5",
            "좋아요_수": "20",
            "댓글_수": "1",
            "영화_제목": "유미의 세포들 더 무비",
            "리뷰_본문_내용": "유미의 행복을 바라면서도\n내 행복은 무엇일까 생각하게 된다.\n내 안의 세포들아 듣고 있니???"
        },
        {
            "리뷰어_닉네임": "어흥",
            "별점": "3.0",
            "좋아요_수": "12",
            "댓글_수": "0",
            "영화_제목": "유미의 세포들 더 무비",
            "리뷰_본문_내용": "불안이가 없었다면 내 인생, 타인에 의해 얼마나 흠났을까."
        },
        {
            "리뷰어_닉네임": "YISO",
            "별점": "3.0",
            "좋아요_수": "12",
            "댓글_수": "0",
            "영화_제목": "유미의 세포들 더 무비",
            "리뷰_본문_내용": "원작을 즐긴 사람이라면 내용적으로 임팩트는 없을지 모르겠다 (갓동건..)\n\n그럼에도 유미와 함께 울던(이것은 관용적 표현이 아니다ㄷㄷ) 그때 생각이 나서 좋았다\n(내 안에 아직 “유미의세포들‘세포'\"가 살아있았더란)\n\n그나저나 나만 웅이 못잊었나\n바비(목소리포함) 유감ㅠㅠ\n\n추억가산점두둑히투척-"
        },
        {
            "리뷰어_닉네임": "맨드로바",
            "별점": "3.0",
            "좋아요_수": "11",
            "댓글_수": "0",
            "영화_제목": "유미의 세포들 더 무비",
            "리뷰_본문_내용": "“‘사랑이’의 마음이 나를 웃음 짓게 했고, ‘불안이’의 걱정이 나를 나아가게 했어.”"
        },
        {
            "리뷰어_닉네임": "ㅇㅈㅇ",
            "별점": "3.0",
            "좋아요_수": "9",
            "댓글_수": "0",
            "영화_제목": "유미의 세포들 더 무비",
            "리뷰_본문_내용": "나의 행복을 위해 각자의 위치에서\n열심히 노력하고 있을\nㅇㅈ의 세포들아,\n고마워."
        },
        {
            "리뷰어_닉네임": "강하람 (캉 더 무비)",
            "별점": "2.5",
            "좋아요_수": "8",
            "댓글_수": "0",
            "영화_제목": "유미의 세포들 더 무비",
            "리뷰_본문_내용": "세포들만으로 보완하기 쉽지 않은 인간 캐릭터"
        },
        {
            "리뷰어_닉네임": "지수_evol",
            "별점": "3.0",
            "좋아요_수": "8",
            "댓글_수": "0",
            "영화_제목": "유미의 세포들 더 무비",
            "리뷰_본문_내용": "사랑이 행복의 전부는 아니지, 어쩌면 불안이 삶을 지탱하게 하는 요소일 수도."
        },
        {
            "리뷰어_닉네임": "임선희",
            "별점": "2.5",
            "좋아요_수": "8",
            "댓글_수": "0",
            "영화_제목": "유미의 세포들 더 무비",
            "리뷰_본문_내용": "내 인생을 위해 헌신하는 오롯이 나를 위한 세포들의 깜찍한 우당탕탕 서사시"
        },
        {
            "리뷰어_닉네임": "시네마타운",
            "별점": "2.0",
            "좋아요_수": "8",
            "댓글_수": "0",
            "영화_제목": "유미의 세포들 더 무비",
            "리뷰_본문_내용": "고생 끝에 마침내 발견한 행복이라는 세포"
        },
        {
            "리뷰어_닉네임": "김다베",
            "별점": "3.0",
            "좋아요_수": "7",
            "댓글_수": "0",
            "영화_제목": "유미의 세포들 더 무비",
            "리뷰_본문_내용": "이렇게 수많은 내가 나를 응원하고 있다는 위로."
        },
        {
            "리뷰어_닉네임": "MissH",
            "별점": "2.5",
            "좋아요_수": "7",
            "댓글_수": "0",
            "영화_제목": "유미의 세포들 더 무비",
            "리뷰_본문_내용": "'유미'는 '바비'가 없어도 괜찮고 \"사랑\"이 1순위가 아니어도 괜찮아. 충분히 행복할 수 있고, 행복할 자격이 있는 '유미'니까.\n\n그리고 '세포들'이 주인공이 된 거 축하한다. 이 영화는 그것만으로 충분한 영화야.🩷💙\n\n[+] 우리나라 애니메이션 진화된 기술력에 많이 놀람. 물 표현하는 게 정말 어렵다는데 이건 해외 애니메이션이랑 비교해도 손색이 없을 정도. 정말 스토리텔링만 좀 더 나아지면 경쟁력이 충분히 있어보이는 것 또한 긍정적으로 보인다."
        },
        {
            "리뷰어_닉네임": "타이거즈",
            "별점": "3.0",
            "좋아요_수": "6",
            "댓글_수": "0",
            "영화_제목": "유미의 세포들 더 무비",
            "리뷰_본문_내용": "유미를 응원해!"
        },
        {
            "리뷰어_닉네임": "수첩",
            "별점": "3.0",
            "좋아요_수": "6",
            "댓글_수": "0",
            "영화_제목": "유미의 세포들 더 무비",
            "리뷰_본문_내용": "그 모든 세포들이 함께 했었기에 얻을 수 있었던 행복이란 세포."
        }
    ]
}